micrograd_andrews/__init__.py
micrograd_andrews/engine.py
micrograd_andrews/nn.py
micrograd_andrews-0.1.8.dist-info/LICENSE
micrograd_andrews-0.1.8.dist-info/WHEEL
micrograd_andrews-0.1.8.dist-info/METADATA
micrograd_andrews-0.1.8.dist-info/RECORD
