Metadata-Version: 2.1
Name: micrograd_andrews
Version: 0.1.8
Summary: Micrograd module by Andrews Peter - A simple branch of Karpathy's micrograd project.
Author-email: Andrews Peter <andrews.peter.business@gmail.com>
Classifier: License :: OSI Approved :: MIT License
Project-URL: Home, https://github.com/karpathy/micrograd
